upper_102218038/__init__.py
upper_102218038/lo2up.py
upper_102218038-2.0.0.dist-info/METADATA
upper_102218038-2.0.0.dist-info/WHEEL
upper_102218038-2.0.0.dist-info/top_level.txt
upper_102218038-2.0.0.dist-info/RECORD
