Metadata-Version: 2.1
Name: upper_102218038
Version: 2.0.0
Summary: Package to convert lowerr case to upper case letter
Author: thebrownkidd
Author-email: <mail@neuralnine.com>
Keywords: python,text,paragraph,lower case,upper case,string
Classifier: Development Status :: 1 - Planning
Classifier: Intended Audience :: Developers
Classifier: Programming Language :: Python :: 3
Classifier: Operating System :: Unix
Classifier: Operating System :: MacOS :: MacOS X
Classifier: Operating System :: Microsoft :: Windows
